samwell/__init__.py
samwell/dnautils.py
samwell/itertools.py
samwell/overlap_detector.py
samwell/sam/__init__.py
samwell/sam/bwa_mem.py
samwell/sam/clipping.py
samwell/sam/sambuilder.py
samwell/sam/tests/__init__.py
samwell/sam/tests/data/valid.sam
samwell/sam/tests/test_bwa_mem.py
samwell/sam/tests/test_clipping.py
samwell/sam/tests/test_sam.py
samwell/sam/tests/test_sambuilder.py
samwell/tests/__init__.py
samwell/tests/test_dnautils.py
samwell/tests/test_itertools.py
samwell/tests/test_overlap_detector.py
samwell-0.0.4.dist-info/LICENSE
samwell-0.0.4.dist-info/WHEEL
samwell-0.0.4.dist-info/METADATA
samwell-0.0.4.dist-info/RECORD
