Metadata-Version: 2.1
Name: samwell
Version: 0.0.4
Summary: Useful utilities for biological data formats and analyses
Author: Jeff Tratner
Author-email: jeffrey.tratner@myriad.com
Requires-Python: >=3.6
Classifier: Programming Language :: Python :: 3
Classifier: Programming Language :: Python :: 3.6
Classifier: Programming Language :: Python :: 3.7
Classifier: Programming Language :: Python :: 3.8
Provides-Extra: docs
Requires-Dist: attrs (>=19.3.0)
Requires-Dist: cython (>=0.29.15)
Requires-Dist: defopt (>=5.1.0)
Requires-Dist: intervaltree (>=3.0.2)
Requires-Dist: mypy-extensions (>=0.4.3)
Requires-Dist: pybedlite (>=0.0.1)
Requires-Dist: pysam (>=0.15.3)
Requires-Dist: sphinx (==4.3.1); extra == "docs"
